{
  "id": "557c06d6-f045-4c73-8b34-05e8d51b5bf2",
  "prevId": "0e63a0db-9e83-4c60-8dd3-0d2c7a367731",
  "version": "7",
  "dialect": "postgresql",
  "tables": {
    "public.app_marketplace_submissions": {
      "name": "app_marketplace_submissions",
      "schema": "",
      "columns": {
        "id": {
          "name": "id",
          "type": "uuid",
          "primaryKey": true,
          "notNull": true,
          "default": "gen_random_uuid()"
        },
        "app_id": {
          "name": "app_id",
          "type": "text",
          "primaryKey": false,
          "notNull": true
        },
        "name": {
          "name": "name",
          "type": "text",
          "primaryKey": false,
          "notNull": true
        },
        "version": {
          "name": "version",
          "type": "text",
          "primaryKey": false,
          "notNull": true
        },
        "source_url": {
          "name": "source_url",
          "type": "text",
          "primaryKey": false,
          "notNull": false
        },
        "manifest": {
          "name": "manifest",
          "type": "jsonb",
          "primaryKey": false,
          "notNull": true
        },
        "status": {
          "name": "status",
          "type": "app_submission_status",
          "typeSchema": "public",
          "primaryKey": false,
          "notNull": true,
          "default": "'pending'"
        },
        "automated_checks": {
          "name": "automated_checks",
          "type": "jsonb",
          "primaryKey": false,
          "notNull": true,
          "default": "'{}'::jsonb"
        },
        "review_notes": {
          "name": "review_notes",
          "type": "text",
          "primaryKey": false,
          "notNull": false
        },
        "submitted_by_user_id": {
          "name": "submitted_by_user_id",
          "type": "uuid",
          "primaryKey": false,
          "notNull": false
        },
        "reviewed_by_user_id": {
          "name": "reviewed_by_user_id",
          "type": "uuid",
          "primaryKey": false,
          "notNull": false
        },
        "reviewed_at": {
          "name": "reviewed_at",
          "type": "timestamp with time zone",
          "primaryKey": false,
          "notNull": false
        },
        "created_at": {
          "name": "created_at",
          "type": "timestamp with time zone",
          "primaryKey": false,
          "notNull": true,
          "default": "now()"
        },
        "updated_at": {
          "name": "updated_at",
          "type": "timestamp with time zone",
          "primaryKey": false,
          "notNull": true,
          "default": "now()"
        }
      },
      "indexes": {},
      "foreignKeys": {
        "app_marketplace_submissions_submitted_by_user_id_users_id_fk": {
          "name": "app_marketplace_submissions_submitted_by_user_id_users_id_fk",
          "tableFrom": "app_marketplace_submissions",
          "tableTo": "users",
          "columnsFrom": [
            "submitted_by_user_id"
          ],
          "columnsTo": [
            "id"
          ],
          "onDelete": "set null",
          "onUpdate": "no action"
        },
        "app_marketplace_submissions_reviewed_by_user_id_users_id_fk": {
          "name": "app_marketplace_submissions_reviewed_by_user_id_users_id_fk",
          "tableFrom": "app_marketplace_submissions",
          "tableTo": "users",
          "columnsFrom": [
            "reviewed_by_user_id"
          ],
          "columnsTo": [
            "id"
          ],
          "onDelete": "set null",
          "onUpdate": "no action"
        }
      },
      "compositePrimaryKeys": {},
      "uniqueConstraints": {},
      "policies": {},
      "checkConstraints": {},
      "isRLSEnabled": false
    },
    "public.community_roles": {
      "name": "community_roles",
      "schema": "",
      "columns": {
        "id": {
          "name": "id",
          "type": "serial",
          "primaryKey": true,
          "notNull": true
        },
        "name": {
          "name": "name",
          "type": "text",
          "primaryKey": false,
          "notNull": true
        },
        "description": {
          "name": "description",
          "type": "text",
          "primaryKey": false,
          "notNull": false
        },
        "permission_role_id": {
          "name": "permission_role_id",
          "type": "integer",
          "primaryKey": false,
          "notNull": true
        },
        "sort_order": {
          "name": "sort_order",
          "type": "integer",
          "primaryKey": false,
          "notNull": true,
          "default": 0
        },
        "created_at": {
          "name": "created_at",
          "type": "timestamp with time zone",
          "primaryKey": false,
          "notNull": true,
          "default": "now()"
        },
        "updated_at": {
          "name": "updated_at",
          "type": "timestamp with time zone",
          "primaryKey": false,
          "notNull": true,
          "default": "now()"
        }
      },
      "indexes": {},
      "foreignKeys": {
        "community_roles_permission_role_id_permission_roles_id_fk": {
          "name": "community_roles_permission_role_id_permission_roles_id_fk",
          "tableFrom": "community_roles",
          "tableTo": "permission_roles",
          "columnsFrom": [
            "permission_role_id"
          ],
          "columnsTo": [
            "id"
          ],
          "onDelete": "restrict",
          "onUpdate": "no action"
        }
      },
      "compositePrimaryKeys": {},
      "uniqueConstraints": {
        "community_roles_name_unique": {
          "name": "community_roles_name_unique",
          "nullsNotDistinct": false,
          "columns": [
            "name"
          ]
        }
      },
      "policies": {},
      "checkConstraints": {},
      "isRLSEnabled": false
    },
    "public.installed_apps": {
      "name": "installed_apps",
      "schema": "",
      "columns": {
        "id": {
          "name": "id",
          "type": "uuid",
          "primaryKey": true,
          "notNull": true,
          "default": "gen_random_uuid()"
        },
        "app_id": {
          "name": "app_id",
          "type": "text",
          "primaryKey": false,
          "notNull": true
        },
        "name": {
          "name": "name",
          "type": "text",
          "primaryKey": false,
          "notNull": true
        },
        "version": {
          "name": "version",
          "type": "text",
          "primaryKey": false,
          "notNull": true
        },
        "status": {
          "name": "status",
          "type": "app_install_status",
          "typeSchema": "public",
          "primaryKey": false,
          "notNull": true,
          "default": "'inactive'"
        },
        "source": {
          "name": "source",
          "type": "app_install_source",
          "typeSchema": "public",
          "primaryKey": false,
          "notNull": true,
          "default": "'sideloaded'"
        },
        "verified": {
          "name": "verified",
          "type": "boolean",
          "primaryKey": false,
          "notNull": true,
          "default": false
        },
        "repository_url": {
          "name": "repository_url",
          "type": "text",
          "primaryKey": false,
          "notNull": false
        },
        "manifest": {
          "name": "manifest",
          "type": "jsonb",
          "primaryKey": false,
          "notNull": true
        },
        "config": {
          "name": "config",
          "type": "jsonb",
          "primaryKey": false,
          "notNull": true,
          "default": "'{}'::jsonb"
        },
        "created_by": {
          "name": "created_by",
          "type": "uuid",
          "primaryKey": false,
          "notNull": false
        },
        "installed_at": {
          "name": "installed_at",
          "type": "timestamp with time zone",
          "primaryKey": false,
          "notNull": true,
          "default": "now()"
        },
        "updated_at": {
          "name": "updated_at",
          "type": "timestamp with time zone",
          "primaryKey": false,
          "notNull": true,
          "default": "now()"
        }
      },
      "indexes": {},
      "foreignKeys": {
        "installed_apps_created_by_users_id_fk": {
          "name": "installed_apps_created_by_users_id_fk",
          "tableFrom": "installed_apps",
          "tableTo": "users",
          "columnsFrom": [
            "created_by"
          ],
          "columnsTo": [
            "id"
          ],
          "onDelete": "set null",
          "onUpdate": "no action"
        }
      },
      "compositePrimaryKeys": {},
      "uniqueConstraints": {
        "installed_apps_app_id_unique": {
          "name": "installed_apps_app_id_unique",
          "nullsNotDistinct": false,
          "columns": [
            "app_id"
          ]
        }
      },
      "policies": {},
      "checkConstraints": {},
      "isRLSEnabled": false
    },
    "public.permission_roles": {
      "name": "permission_roles",
      "schema": "",
      "columns": {
        "id": {
          "name": "id",
          "type": "serial",
          "primaryKey": true,
          "notNull": true
        },
        "name": {
          "name": "name",
          "type": "text",
          "primaryKey": false,
          "notNull": true
        },
        "description": {
          "name": "description",
          "type": "text",
          "primaryKey": false,
          "notNull": false
        },
        "level": {
          "name": "level",
          "type": "integer",
          "primaryKey": false,
          "notNull": true,
          "default": 0
        }
      },
      "indexes": {},
      "foreignKeys": {},
      "compositePrimaryKeys": {},
      "uniqueConstraints": {
        "permission_roles_name_unique": {
          "name": "permission_roles_name_unique",
          "nullsNotDistinct": false,
          "columns": [
            "name"
          ]
        }
      },
      "policies": {},
      "checkConstraints": {},
      "isRLSEnabled": false
    },
    "public.profile_change_log": {
      "name": "profile_change_log",
      "schema": "",
      "columns": {
        "id": {
          "name": "id",
          "type": "uuid",
          "primaryKey": true,
          "notNull": true,
          "default": "gen_random_uuid()"
        },
        "profile_id": {
          "name": "profile_id",
          "type": "uuid",
          "primaryKey": false,
          "notNull": true
        },
        "change_type": {
          "name": "change_type",
          "type": "text",
          "primaryKey": false,
          "notNull": true
        },
        "previous_value": {
          "name": "previous_value",
          "type": "text",
          "primaryKey": false,
          "notNull": false
        },
        "new_value": {
          "name": "new_value",
          "type": "text",
          "primaryKey": false,
          "notNull": false
        },
        "is_growth": {
          "name": "is_growth",
          "type": "boolean",
          "primaryKey": false,
          "notNull": true,
          "default": false
        },
        "is_departure": {
          "name": "is_departure",
          "type": "boolean",
          "primaryKey": false,
          "notNull": true,
          "default": false
        },
        "changed_by": {
          "name": "changed_by",
          "type": "uuid",
          "primaryKey": false,
          "notNull": false
        },
        "created_at": {
          "name": "created_at",
          "type": "timestamp with time zone",
          "primaryKey": false,
          "notNull": true,
          "default": "now()"
        }
      },
      "indexes": {},
      "foreignKeys": {
        "profile_change_log_profile_id_profiles_id_fk": {
          "name": "profile_change_log_profile_id_profiles_id_fk",
          "tableFrom": "profile_change_log",
          "tableTo": "profiles",
          "columnsFrom": [
            "profile_id"
          ],
          "columnsTo": [
            "id"
          ],
          "onDelete": "cascade",
          "onUpdate": "no action"
        },
        "profile_change_log_changed_by_users_id_fk": {
          "name": "profile_change_log_changed_by_users_id_fk",
          "tableFrom": "profile_change_log",
          "tableTo": "users",
          "columnsFrom": [
            "changed_by"
          ],
          "columnsTo": [
            "id"
          ],
          "onDelete": "set null",
          "onUpdate": "no action"
        }
      },
      "compositePrimaryKeys": {},
      "uniqueConstraints": {},
      "policies": {},
      "checkConstraints": {},
      "isRLSEnabled": false
    },
    "public.profiles": {
      "name": "profiles",
      "schema": "",
      "columns": {
        "id": {
          "name": "id",
          "type": "uuid",
          "primaryKey": true,
          "notNull": true,
          "default": "gen_random_uuid()"
        },
        "user_id": {
          "name": "user_id",
          "type": "uuid",
          "primaryKey": false,
          "notNull": true
        },
        "bio": {
          "name": "bio",
          "type": "text",
          "primaryKey": false,
          "notNull": false
        },
        "absence_status": {
          "name": "absence_status",
          "type": "absence_status",
          "typeSchema": "public",
          "primaryKey": false,
          "notNull": false
        },
        "absence_message": {
          "name": "absence_message",
          "type": "text",
          "primaryKey": false,
          "notNull": false
        },
        "absence_until": {
          "name": "absence_until",
          "type": "timestamp with time zone",
          "primaryKey": false,
          "notNull": false
        },
        "custom_fields": {
          "name": "custom_fields",
          "type": "jsonb",
          "primaryKey": false,
          "notNull": false,
          "default": "'{}'::jsonb"
        },
        "updated_at": {
          "name": "updated_at",
          "type": "timestamp with time zone",
          "primaryKey": false,
          "notNull": true,
          "default": "now()"
        }
      },
      "indexes": {},
      "foreignKeys": {
        "profiles_user_id_users_id_fk": {
          "name": "profiles_user_id_users_id_fk",
          "tableFrom": "profiles",
          "tableTo": "users",
          "columnsFrom": [
            "user_id"
          ],
          "columnsTo": [
            "id"
          ],
          "onDelete": "cascade",
          "onUpdate": "no action"
        }
      },
      "compositePrimaryKeys": {},
      "uniqueConstraints": {
        "profiles_user_id_unique": {
          "name": "profiles_user_id_unique",
          "nullsNotDistinct": false,
          "columns": [
            "user_id"
          ]
        }
      },
      "policies": {},
      "checkConstraints": {},
      "isRLSEnabled": false
    },
    "public.user_community_roles": {
      "name": "user_community_roles",
      "schema": "",
      "columns": {
        "user_id": {
          "name": "user_id",
          "type": "uuid",
          "primaryKey": false,
          "notNull": true
        },
        "community_role_id": {
          "name": "community_role_id",
          "type": "integer",
          "primaryKey": false,
          "notNull": true
        },
        "assigned_at": {
          "name": "assigned_at",
          "type": "timestamp with time zone",
          "primaryKey": false,
          "notNull": true,
          "default": "now()"
        }
      },
      "indexes": {},
      "foreignKeys": {
        "user_community_roles_user_id_users_id_fk": {
          "name": "user_community_roles_user_id_users_id_fk",
          "tableFrom": "user_community_roles",
          "tableTo": "users",
          "columnsFrom": [
            "user_id"
          ],
          "columnsTo": [
            "id"
          ],
          "onDelete": "cascade",
          "onUpdate": "no action"
        },
        "user_community_roles_community_role_id_community_roles_id_fk": {
          "name": "user_community_roles_community_role_id_community_roles_id_fk",
          "tableFrom": "user_community_roles",
          "tableTo": "community_roles",
          "columnsFrom": [
            "community_role_id"
          ],
          "columnsTo": [
            "id"
          ],
          "onDelete": "restrict",
          "onUpdate": "no action"
        }
      },
      "compositePrimaryKeys": {},
      "uniqueConstraints": {
        "user_community_roles_user_id_unique": {
          "name": "user_community_roles_user_id_unique",
          "nullsNotDistinct": false,
          "columns": [
            "user_id"
          ]
        }
      },
      "policies": {},
      "checkConstraints": {},
      "isRLSEnabled": false
    },
    "public.user_permission_roles": {
      "name": "user_permission_roles",
      "schema": "",
      "columns": {
        "user_id": {
          "name": "user_id",
          "type": "uuid",
          "primaryKey": false,
          "notNull": true
        },
        "permission_role_id": {
          "name": "permission_role_id",
          "type": "integer",
          "primaryKey": false,
          "notNull": true
        },
        "assigned_at": {
          "name": "assigned_at",
          "type": "timestamp with time zone",
          "primaryKey": false,
          "notNull": true,
          "default": "now()"
        }
      },
      "indexes": {},
      "foreignKeys": {
        "user_permission_roles_user_id_users_id_fk": {
          "name": "user_permission_roles_user_id_users_id_fk",
          "tableFrom": "user_permission_roles",
          "tableTo": "users",
          "columnsFrom": [
            "user_id"
          ],
          "columnsTo": [
            "id"
          ],
          "onDelete": "cascade",
          "onUpdate": "no action"
        },
        "user_permission_roles_permission_role_id_permission_roles_id_fk": {
          "name": "user_permission_roles_permission_role_id_permission_roles_id_fk",
          "tableFrom": "user_permission_roles",
          "tableTo": "permission_roles",
          "columnsFrom": [
            "permission_role_id"
          ],
          "columnsTo": [
            "id"
          ],
          "onDelete": "cascade",
          "onUpdate": "no action"
        }
      },
      "compositePrimaryKeys": {
        "user_permission_roles_user_id_permission_role_id_pk": {
          "name": "user_permission_roles_user_id_permission_role_id_pk",
          "columns": [
            "user_id",
            "permission_role_id"
          ]
        }
      },
      "uniqueConstraints": {},
      "policies": {},
      "checkConstraints": {},
      "isRLSEnabled": false
    },
    "public.users": {
      "name": "users",
      "schema": "",
      "columns": {
        "id": {
          "name": "id",
          "type": "uuid",
          "primaryKey": true,
          "notNull": true,
          "default": "gen_random_uuid()"
        },
        "discord_id": {
          "name": "discord_id",
          "type": "text",
          "primaryKey": false,
          "notNull": true
        },
        "email": {
          "name": "email",
          "type": "text",
          "primaryKey": false,
          "notNull": false
        },
        "display_name": {
          "name": "display_name",
          "type": "text",
          "primaryKey": false,
          "notNull": true
        },
        "nickname": {
          "name": "nickname",
          "type": "text",
          "primaryKey": false,
          "notNull": false
        },
        "avatar_url": {
          "name": "avatar_url",
          "type": "text",
          "primaryKey": false,
          "notNull": false
        },
        "created_at": {
          "name": "created_at",
          "type": "timestamp with time zone",
          "primaryKey": false,
          "notNull": true,
          "default": "now()"
        },
        "updated_at": {
          "name": "updated_at",
          "type": "timestamp with time zone",
          "primaryKey": false,
          "notNull": true,
          "default": "now()"
        }
      },
      "indexes": {},
      "foreignKeys": {},
      "compositePrimaryKeys": {},
      "uniqueConstraints": {
        "users_discord_id_unique": {
          "name": "users_discord_id_unique",
          "nullsNotDistinct": false,
          "columns": [
            "discord_id"
          ]
        }
      },
      "policies": {},
      "checkConstraints": {},
      "isRLSEnabled": false
    },
    "public.voice_sessions": {
      "name": "voice_sessions",
      "schema": "",
      "columns": {
        "id": {
          "name": "id",
          "type": "uuid",
          "primaryKey": true,
          "notNull": true,
          "default": "gen_random_uuid()"
        },
        "user_id": {
          "name": "user_id",
          "type": "uuid",
          "primaryKey": false,
          "notNull": true
        },
        "channel_id": {
          "name": "channel_id",
          "type": "text",
          "primaryKey": false,
          "notNull": false
        },
        "started_at": {
          "name": "started_at",
          "type": "timestamp with time zone",
          "primaryKey": false,
          "notNull": true
        },
        "ended_at": {
          "name": "ended_at",
          "type": "timestamp with time zone",
          "primaryKey": false,
          "notNull": false
        },
        "duration_minutes": {
          "name": "duration_minutes",
          "type": "integer",
          "primaryKey": false,
          "notNull": false
        },
        "created_at": {
          "name": "created_at",
          "type": "timestamp with time zone",
          "primaryKey": false,
          "notNull": true,
          "default": "now()"
        }
      },
      "indexes": {},
      "foreignKeys": {
        "voice_sessions_user_id_users_id_fk": {
          "name": "voice_sessions_user_id_users_id_fk",
          "tableFrom": "voice_sessions",
          "tableTo": "users",
          "columnsFrom": [
            "user_id"
          ],
          "columnsTo": [
            "id"
          ],
          "onDelete": "cascade",
          "onUpdate": "no action"
        }
      },
      "compositePrimaryKeys": {},
      "uniqueConstraints": {},
      "policies": {},
      "checkConstraints": {},
      "isRLSEnabled": false
    }
  },
  "enums": {
    "public.absence_status": {
      "name": "absence_status",
      "schema": "public",
      "values": [
        "away",
        "maintenance"
      ]
    },
    "public.app_install_source": {
      "name": "app_install_source",
      "schema": "public",
      "values": [
        "marketplace",
        "sideloaded"
      ]
    },
    "public.app_install_status": {
      "name": "app_install_status",
      "schema": "public",
      "values": [
        "active",
        "inactive",
        "error"
      ]
    },
    "public.app_submission_status": {
      "name": "app_submission_status",
      "schema": "public",
      "values": [
        "pending",
        "approved",
        "rejected"
      ]
    }
  },
  "schemas": {},
  "sequences": {},
  "roles": {},
  "policies": {},
  "views": {},
  "_meta": {
    "columns": {},
    "schemas": {},
    "tables": {}
  }
}